OOTUI/BorderRect.py
OOTUI/Characters.py
OOTUI/Rect.py
OOTUI/ScalableWindow.py
OOTUI/SuperDrawable.py
OOTUI/Vector2.py
OOTUI/Window.py
OOTUI/__init__.py
OOTUI/objects.py
OOTUI-0.0.1.2.dist-info/METADATA
OOTUI-0.0.1.2.dist-info/WHEEL
OOTUI-0.0.1.2.dist-info/top_level.txt
OOTUI-0.0.1.2.dist-info/RECORD
