Metadata-Version: 2.1
Name: OOTUI
Version: 0.0.1.2
Summary: Object-Oriented Terminal User Interface an object oriented way of displaying data in the terminal.
Home-page: https://github.com/jorrit200/OOTUI
Author: Jorrit200
Author-email: haanelijk2@gmail.com
License: UNKNOWN
Platform: UNKNOWN
Classifier: Programming Language :: Python :: 3
Classifier: License :: OSI Approved :: MIT License
Classifier: Operating System :: OS Independent
Requires-Python: >=3.6
